README.md
setup.py
bin/dissipate
dissipate/__init__.py
dissipate.egg-info/PKG-INFO
dissipate.egg-info/SOURCES.txt
dissipate.egg-info/dependency_links.txt
dissipate.egg-info/top_level.txt