Metadata-Version: 2.1
Name: dissipate
Version: 0.0.1
Summary: dissipate
Home-page: https://github.com/vanessafkim1997/compete
Author: davidypage1993
Author-email: davidypage1993@outlook.com
License: UNKNOWN
Platform: UNKNOWN
Classifier: Programming Language :: Python :: 3
Classifier: License :: OSI Approved :: MIT License
Classifier: Operating System :: OS Independent
